CHANGES.rst
MANIFEST.in
Makefile
README.rst
setup.py
tests.py
tmp.py
tmp.egg-info/PKG-INFO
tmp.egg-info/SOURCES.txt
tmp.egg-info/dependency_links.txt
tmp.egg-info/entry_points.txt
tmp.egg-info/not-zip-safe
tmp.egg-info/top_level.txt