Metadata-Version: 1.1
Name: tmp
Version: 0.0.2
Summary: Make a temp dir
Home-page: https://github.com/aclark4life/tmp
Author: Alex Clark
Author-email: aclark@aclark.net
License: GPL
Keywords: temp temporary files directory
Platform: UNKNOWN
Classifier: Programming Language :: Python :: 2.7
Classifier: Programming Language :: Python :: 3.3
